<annotation>
	<folder>UAV_data</folder>
	<filename>20161226-SPI-AOI-12_180.jpg</filename>
	<source>
		<database>The UAV autolanding</database>
		<annotation>UAV AutoLanding</annotation>
		<image>flickr</image>
		<flickrid>NULL</flickrid>
	</source>
	<owner>
		<flickrid>NULL</flickrid>
		<name>ChaojieZhu</name>
	</owner>
	<size>
		<width>600</width>
		<height>600</height>
		<depth>3</depth>
	</size>
		<segmented>0</segmented>
	<object>
		<name>Bad_qiaojiao</name>
		<pose>Unspecified</pose>
		<truncated>0</truncated>
		<difficult>0</difficult>
		<bndbox>
			<xmin>519</xmin>
			<ymin>457</ymin>
			<xmax>562</xmax>
			<ymax>461</ymax>
		</bndbox>
	</object>
	<object>
		<name>Bad_podu</name>
		<pose>Unspecified</pose>
		<truncated>0</truncated>
		<difficult>0</difficult>
		<bndbox>
			<xmin>555</xmin>
			<ymin>449</ymin>
			<xmax>567</xmax>
			<ymax>458</ymax>
		</bndbox>
	</object>
	<object>
		<name>Bad_qiaojiao</name>
		<pose>Unspecified</pose>
		<truncated>0</truncated>
		<difficult>0</difficult>
		<bndbox>
			<xmin>530</xmin>
			<ymin>427</ymin>
			<xmax>561</xmax>
			<ymax>432</ymax>
		</bndbox>
	</object>
	<object>
		<name>Bad_podu</name>
		<pose>Unspecified</pose>
		<truncated>0</truncated>
		<difficult>0</difficult>
		<bndbox>
			<xmin>556</xmin>
			<ymin>420</ymin>
			<xmax>568</xmax>
			<ymax>429</ymax>
		</bndbox>
	</object>
	<object>
		<name>Bad_podu</name>
		<pose>Unspecified</pose>
		<truncated>0</truncated>
		<difficult>0</difficult>
		<bndbox>
			<xmin>556</xmin>
			<ymin>391</ymin>
			<xmax>567</xmax>
			<ymax>401</ymax>
		</bndbox>
	</object>
	<object>
		<name>Bad_qiaojiao</name>
		<pose>Unspecified</pose>
		<truncated>0</truncated>
		<difficult>0</difficult>
		<bndbox>
			<xmin>533</xmin>
			<ymin>399</ymin>
			<xmax>561</xmax>
			<ymax>404</ymax>
		</bndbox>
	</object>
</annotation>