<annotation>
	<folder>UAV_data</folder>
	<filename>20161102-SPI-AOI-9_suofang.jpg</filename>
	<source>
		<database>The UAV autolanding</database>
		<annotation>UAV AutoLanding</annotation>
		<image>flickr</image>
		<flickrid>NULL</flickrid>
	</source>
	<owner>
		<flickrid>NULL</flickrid>
		<name>ChaojieZhu</name>
	</owner>
	<size>
		<width>900</width>
		<height>900</height>
		<depth>3</depth>
	</size>
		<segmented>0</segmented>
	<object>
		<name>Bad_qiaojiao</name>
		<pose>Unspecified</pose>
		<truncated>0</truncated>
		<difficult>0</difficult>
		<bndbox>
			<xmin>606</xmin>
			<ymin>788</ymin>
			<xmax>613</xmax>
			<ymax>850</ymax>
		</bndbox>
	</object>
	<object>
		<name>Bad_podu</name>
		<pose>Unspecified</pose>
		<truncated>0</truncated>
		<difficult>0</difficult>
		<bndbox>
			<xmin>592</xmin>
			<ymin>843</ymin>
			<xmax>606</xmax>
			<ymax>863</ymax>
		</bndbox>
	</object>
	<object>
		<name>Bad_qiaojiao</name>
		<pose>Unspecified</pose>
		<truncated>0</truncated>
		<difficult>0</difficult>
		<bndbox>
			<xmin>647</xmin>
			<ymin>786</ymin>
			<xmax>656</xmax>
			<ymax>850</ymax>
		</bndbox>
	</object>
	<object>
		<name>Bad_podu</name>
		<pose>Unspecified</pose>
		<truncated>0</truncated>
		<difficult>0</difficult>
		<bndbox>
			<xmin>677</xmin>
			<ymin>845</ymin>
			<xmax>690</xmax>
			<ymax>861</ymax>
		</bndbox>
	</object>
	<object>
		<name>Bad_qiaojiao</name>
		<pose>Unspecified</pose>
		<truncated>0</truncated>
		<difficult>0</difficult>
		<bndbox>
			<xmin>690</xmin>
			<ymin>776</ymin>
			<xmax>700</xmax>
			<ymax>851</ymax>
		</bndbox>
	</object>
	<object>
		<name>Bad_podu</name>
		<pose>Unspecified</pose>
		<truncated>0</truncated>
		<difficult>0</difficult>
		<bndbox>
			<xmin>633</xmin>
			<ymin>844</ymin>
			<xmax>647</xmax>
			<ymax>862</ymax>
		</bndbox>
	</object>
</annotation>