<annotation>
	<folder>UAV_data</folder>
	<filename>20170112-SPI-AOI-2_180.jpg</filename>
	<source>
		<database>The UAV autolanding</database>
		<annotation>UAV AutoLanding</annotation>
		<image>flickr</image>
		<flickrid>NULL</flickrid>
	</source>
	<owner>
		<flickrid>NULL</flickrid>
		<name>ChaojieZhu</name>
	</owner>
	<size>
		<width>600</width>
		<height>600</height>
		<depth>3</depth>
	</size>
		<segmented>0</segmented>
	<object>
		<name>Bad_podu</name>
		<pose>Unspecified</pose>
		<truncated>0</truncated>
		<difficult>0</difficult>
		<bndbox>
			<xmin>260</xmin>
			<ymin>527</ymin>
			<xmax>271</xmax>
			<ymax>547</ymax>
		</bndbox>
	</object>
	<object>
		<name>Bad_podu</name>
		<pose>Unspecified</pose>
		<truncated>0</truncated>
		<difficult>0</difficult>
		<bndbox>
			<xmin>220</xmin>
			<ymin>522</ymin>
			<xmax>234</xmax>
			<ymax>546</ymax>
		</bndbox>
	</object>
	<object>
		<name>Bad_podu</name>
		<pose>Unspecified</pose>
		<truncated>0</truncated>
		<difficult>0</difficult>
		<bndbox>
			<xmin>182</xmin>
			<ymin>524</ymin>
			<xmax>194</xmax>
			<ymax>547</ymax>
		</bndbox>
	</object>
	<object>
		<name>Bad_podu</name>
		<pose>Unspecified</pose>
		<truncated>0</truncated>
		<difficult>0</difficult>
		<bndbox>
			<xmin>143</xmin>
			<ymin>525</ymin>
			<xmax>155</xmax>
			<ymax>549</ymax>
		</bndbox>
	</object>
	<object>
		<name>Bad_podu</name>
		<pose>Unspecified</pose>
		<truncated>0</truncated>
		<difficult>0</difficult>
		<bndbox>
			<xmin>104</xmin>
			<ymin>523</ymin>
			<xmax>116</xmax>
			<ymax>546</ymax>
		</bndbox>
	</object>
	<object>
		<name>Bad_podu</name>
		<pose>Unspecified</pose>
		<truncated>0</truncated>
		<difficult>0</difficult>
		<bndbox>
			<xmin>459</xmin>
			<ymin>31</ymin>
			<xmax>471</xmax>
			<ymax>56</ymax>
		</bndbox>
	</object>
	<object>
		<name>Bad_podu</name>
		<pose>Unspecified</pose>
		<truncated>0</truncated>
		<difficult>0</difficult>
		<bndbox>
			<xmin>420</xmin>
			<ymin>29</ymin>
			<xmax>432</xmax>
			<ymax>60</ymax>
		</bndbox>
	</object>
	<object>
		<name>Bad_qiaojiao</name>
		<pose>Unspecified</pose>
		<truncated>0</truncated>
		<difficult>0</difficult>
		<bndbox>
			<xmin>413</xmin>
			<ymin>42</ymin>
			<xmax>418</xmax>
			<ymax>90</ymax>
		</bndbox>
	</object>
</annotation>